aurora_dsql_tortoise/__init__.py
aurora_dsql_tortoise/_version.py
aurora_dsql_tortoise/py.typed
aurora_dsql_tortoise/aerich/__init__.py
aurora_dsql_tortoise/aerich/patch.py
aurora_dsql_tortoise/asyncpg/__init__.py
aurora_dsql_tortoise/asyncpg/client.py
aurora_dsql_tortoise/asyncpg/schema_generator.py
aurora_dsql_tortoise/common/__init__.py
aurora_dsql_tortoise/common/config.py
aurora_dsql_tortoise/common/schema_generator.py
aurora_dsql_tortoise/psycopg/__init__.py
aurora_dsql_tortoise/psycopg/client.py
aurora_dsql_tortoise/psycopg/schema_generator.py
aurora_dsql_tortoise_orm-0.1.4.dist-info/METADATA
aurora_dsql_tortoise_orm-0.1.4.dist-info/WHEEL
aurora_dsql_tortoise_orm-0.1.4.dist-info/entry_points.txt
aurora_dsql_tortoise_orm-0.1.4.dist-info/RECORD
