Metadata-Version: 2.4
Name: aurora-dsql-tortoise-orm
Version: 0.1.4
Summary: Aurora DSQL adapter for Tortoise ORM
Project-URL: Repository, https://github.com/awslabs/aurora-dsql-orms
Project-URL: Documentation, https://github.com/awslabs/aurora-dsql-orms/tree/main/python/tortoise-orm
Author: Amazon Web Services
License-Expression: Apache-2.0
Classifier: Intended Audience :: Developers
Classifier: License :: OSI Approved :: Apache Software License
Classifier: Programming Language :: Python
Classifier: Programming Language :: Python :: 3.10
Classifier: Programming Language :: Python :: 3.11
Classifier: Programming Language :: Python :: 3.12
Classifier: Programming Language :: Python :: 3.13
Classifier: Programming Language :: Python :: 3.14
Requires-Python: >=3.10
Requires-Dist: aurora-dsql-python-connector
Provides-Extra: asyncpg
Requires-Dist: tortoise-orm[asyncpg]>=0.25; extra == 'asyncpg'
Provides-Extra: psycopg
Requires-Dist: tortoise-orm[psycopg]>=0.25; extra == 'psycopg'
